{"1 msg by lm":"\u0007ff1414ff[Skeerty] \u0007c8c8c8ffChat have been cleared.","6 messange & hwid 5139546030":"Сергей Шарлотка:    ","18 messange & hwid admin please soso my penis":"admin: ?","7 messange & hwid 5139546030":"Сергей Шарлотка: ne pishet na russkom","11 messange & hwid 5216078295":"arseny047: hhhhhh","4 messange & hwid 5139546030":"Сергей Шарлотка: piska","13 messange & hwid 5168776242":"кастрирован: suka","30 messange & hwid admin please soso my penis":"admin: ?","20 messange & hwid admin please soso my penis":"admin: ?","10 messange & hwid 5216078295":"arseny047: 4","16 messange & hwid 5144819466":"яйка теч: .","8 messange & hwid 5226329718":"?): так рендер чата вруби","12 messange & hwid 5168776242":"кастрирован: suka","22 messange & hwid admin please soso my penis":"admin: ?","21 messange & hwid admin please soso my penis":"admin: ?","5 messange & hwid 5226329718":"?): а че ты на руccком не хоч?","24 messange & hwid admin please soso my penis":"admin: ?","29 messange & hwid admin please soso my penis":"admin: ?","23 messange & hwid admin please soso my penis":"admin: ?","28 messange & hwid admin please soso my penis":"admin: ?","26 messange & hwid admin please soso my penis":"admin: ?","9 messange & hwid 5226329718":"?): и там уже пиши боше","25 messange & hwid admin please soso my penis":"admin: ?","14 messange & hwid 5137120770":"zudx (snep): guhh","3 messange & hwid 5226329718":"?): ","15 messange & hwid 5137120770":"zudx (snep): who wanna 1x1","27 messange & hwid admin please soso my penis":"admin: ?","17 messange & hwid admin please soso my penis":"admin: ?","19 messange & hwid admin please soso my penis":"admin: ?","2 messange & hwid 5226329718":"?): Привет вcем!"}